{
  /* Auth Info requires creating a Bot which can be done through https://discordapp.com/developers/applications/ (Make sure to give it Administrator Perms)*/
  /* Auth info */
  "token": "Y O U R _ B O T _ T O K E N",

  // Unused
  "invite": "InviteLink",
  "gmail": "YourGmailAdress",
  "gmailPassword": "YourGmailPassword",

  /* 'SSL MODE' and 'Allow User Variables' are only required when running on a local machine with XAMPP. This can often be removed. */
  /* DB Info*/
  "DbConnectionString": "server=localhost;port=3306;database=test;user id=USER;Password=USERPASSWORD;SSL Mode=None;Allow User Variables=True",
  /*Server Info*/
  "serverRootPath": "./SERVER",
  /* Base info */
  "prefix": "!",
  "allowMentionPrefix": "1",
  "Administrator": "id",
  "guildId": "493510779866316801", // Replace this with your Servers ID
  // id
  "TNTDroid": "id",
  // id

  /* Send a message when a user joins */
  "sendJoinMessage": "1",
  "sendMessage": "User {0} has joined the server!",
  "deleteProfileMessageCache": "1",
  /* Remove the messages after x seconds */
  "deleteProfileMessageCacheTime": "1",
  /* All roles */
  "rolesUser": {
    "desc": "All normal user assignable roles available",
    "roles": [
      "3DModelers",
      "Artists",
      "BetaTester",
      "Coders",
      "C#",
      "JavaScript",
      "Game-Designers",
      "Audio-Artists",
      "Generalists",
      "Hobbyists",
      "Vector-Artists",
      "Voxel-Artists",
      "Students",
      "VR-Developers",
      "Streamer"
    ]
  },
  /* Roles the bot cannot touch */
  "rolesBanned": {
    "desc": "Roles that are banned from the bot to assign.",
    "roles": [
      "Administrator",
      "ModSquad",
      "Bots",
      "Enforcers",
      "@everyone",
      "Publishers",
      "Helpers",
      "Mod-Artists",
      "Mod-Coders",
      "Mod-Helpers",
      "Streaming",
      "Patreon",
      "Patreon-Bot",
      "Overwatch",
      "UnityOfficial",
      "Carbon"
    ]
  },
  /* Roles the bot can assign if initiated by ModSquad user */
  "rolesModeration": {
    "desc": "Roles that are used for moderation.",
    "roles": [
      "Muted",
      "Mute-hire-you",
      "Mute-hire-me",
      "Mute-collab"
    ]
  },
  /* Modsqaud */
  "roleModSquadPermission": {
    "desc": "roles that have ability to use modsquad commands",
    "roles": [
      "Administrator",
      "ModSquad",
      "Mod-Artists",
      "Mod-Coders",
      "Mod-Helpers",
      "Enforcers"
    ]
  },
  /* Channels */
  "serverID": {
    "desc": "Unity Developer Hub - General-Chat",
    "id": "493511009256996875"
  },
  "generalChannel": {
    "desc": "General-Chat Channel",
    "id": "493511024037724180"
  },
  "botDevelopmentChannel": {
    "desc": "Bot-Development Channel",
    "id": "206821282258485248"
  },
  "botFunctionalityChannel": {
    "desc": "Bot-Functionality Channel",
    "id": "256411017842655236"
  },
  "botAnnouncementChannel": {
    "desc": "Bot-Announcement Channel",
    "id": "213177844833058817"
  },
  "botXPMessageChannel": {
    "desc": "Bot-XPMessage Channel",
    "id": "260416365092012032"
  },
  "announcementsChannel": {
    "desc": "General Announcement Channel",
    "id": "206846565925650432"
  },
  "botCommandsChannel": {
    "desc": "Bot-Commands Channel",
    "id": "207741022262919170"
  },
  "botPublisherPrivateChannel": {
    "desc": "Publisher Private Channel",
    "id": "217940497275158529"
  },
  "unityNewsChannel": {
    "desc": "Unity News Channel",
    "id": "493511009256996875"
  },
  "botPrivateChannel": {
    "desc": "Admin Private Channel",
    "id": "213610663472398336"
  },
  "devStreamChannel": {
    "desc": "Dev-Stream Channel",
    "id": "234188067194273793"
  },
  "workForHireChannel": {
    "desc": "Work For Hire Channel",
    "id": "206829581041139712"
  },
  "collaborationChannel": {
    "desc": "Collaboration Channel",
    "id": "264335890791339425"
  },
  "animeChannel": {
    "desc": "Anime Channel",
    "id": "567628191221547008"
  },
  "casinoChannel": {
    "desc": "Casino Channel",
    "id": "428675701596749824"
  },
  "musicCommandsChannel": {
    "desc": "Music Commands Channel",
    "id": "432242383606906891"
  },
  /* Role Ids */
  "mutedRoleID": "221120789544435714",
  "streamingRoleID": "233830762883842048",
  "streamerRoleID": "233814950710214659",
  "publisherRoleID": "206830803575898112",
  "staffRoleId": "460573273134989313",
  "SubsNewsRoleId": "0",
  "SubsReleasesRoleId": "0",
  /*Publisher Stuff*/
  "assetStoreFrontPage": "https://www.assetstore.unity3d.com/en/",
  /*Complaints Channels Stuff*/
  "complaintCategoryName": "Complaints",
  "complaintChannelPrefix": "Complaint",
  /*Commands Configuration*/
  "wikipediaSearchPage": "https://en.wikipedia.org/w/api.php?format=json&action=opensearch&profile=fuzzy&limit=5&redirects=resolve&search="
}